{
  "indexes": [
    {
      "collectionGroup": "locations",
      "queryScope": "COLLECTION",
      "fields": [
        { "fieldPath": "accessCode", "order": "ASCENDING" },
        { "fieldPath": "isActive", "order": "ASCENDING" }
      ]
    },
    {
      "collectionGroup": "bookings",
      "queryScope": "COLLECTION",
      "fields": [
        { "fieldPath": "locationId", "order": "ASCENDING" },
        { "fieldPath": "bookingDate", "order": "ASCENDING" },
        { "fieldPath": "status", "order": "ASCENDING" }
      ]
    },
    {
      "collectionGroup": "bookings",
      "queryScope": "COLLECTION",
      "fields": [
        { "fieldPath": "bookingDate", "order": "ASCENDING" },
        { "fieldPath": "status", "order": "ASCENDING" }
      ]
    }
  ],
  "fieldOverrides": []
}